goss/__init__.py
goss/client.py
goss/comm.py
goss/exception.py
goss/cloud/__init__.py
goss/cloud/aliyun_oss.py
goss/cloud/amazon_s3.py
goss/cloud/azure_blob.py
goss/cloud/huaweicloud_obs.py
goss/cloud/tencent_cos.py
goss_sdk_python-0.7.7.dist-info/LICENSE
goss_sdk_python-0.7.7.dist-info/METADATA
goss_sdk_python-0.7.7.dist-info/WHEEL
goss_sdk_python-0.7.7.dist-info/top_level.txt
goss_sdk_python-0.7.7.dist-info/RECORD
